flexup/__init__.py
flexup/server.py
flexup-0.2.0.dist-info/licenses/LICENSE
flexup-0.2.0.dist-info/METADATA
flexup-0.2.0.dist-info/WHEEL
flexup-0.2.0.dist-info/entry_points.txt
flexup-0.2.0.dist-info/top_level.txt
flexup-0.2.0.dist-info/RECORD
