Metadata-Version: 2.4
Name: flexup
Version: 0.2.0
Summary: A flexible file upload server with Flask and predefined upload destinations
Author-email: dyay108 <dyay108@users.noreply.github.com>
License: MIT
Project-URL: Homepage, https://github.com/dyay108/flexup
Project-URL: Documentation, https://github.com/dyay108/flexup#readme
Project-URL: Repository, https://github.com/dyay108/flexup
Project-URL: Bug Tracker, https://github.com/dyay108/flexup/issues
Keywords: flexup,upload,server,flask,file-transfer
Classifier: Development Status :: 3 - Alpha
Classifier: Intended Audience :: Developers
Classifier: License :: OSI Approved :: MIT License
Classifier: Programming Language :: Python :: 3
Classifier: Programming Language :: Python :: 3.8
Classifier: Programming Language :: Python :: 3.9
Classifier: Programming Language :: Python :: 3.10
Classifier: Programming Language :: Python :: 3.11
Classifier: Programming Language :: Python :: 3.12
Classifier: Framework :: Flask
Requires-Python: >=3.8
License-File: LICENSE
Requires-Dist: flask>=2.0.0
Requires-Dist: werkzeug>=2.0.0
Provides-Extra: dev
Requires-Dist: pytest>=7.0; extra == "dev"
Requires-Dist: pytest-cov>=4.0; extra == "dev"
Requires-Dist: black>=23.0; extra == "dev"
Requires-Dist: flake8>=6.0; extra == "dev"
Requires-Dist: mypy>=1.0; extra == "dev"
Dynamic: license-file
